idegui/__init__.py
idegui/__main__.py
idegui/popup.py
idegui/window.py
idegui-1.0.2.dist-info/LICENSE
idegui-1.0.2.dist-info/METADATA
idegui-1.0.2.dist-info/WHEEL
idegui-1.0.2.dist-info/top_level.txt
idegui-1.0.2.dist-info/RECORD
