Metadata-Version: 2.1
Name: idegui
Version: 1.0.2
Summary: a library for write an IDE
Home-page: UNKNOWN
Author: stripe-python
Author-email: 13513519246@139.com
License: UNKNOWN
Platform: UNKNOWN
Requires-Dist: chardet
